{
  "ApiName": "VMC",
  "ApiScheme": "https",
  "ApiUrl": "vmc.vmware.com",
  "Resources": {
    "AccountLink": {
      "Path": "/vmc/api/orgs/{org}/account-link",
      "Method": [
        "GET"
      ]
    },
    "AwsSddcConnections": {
      "Path": "/vmc/api/orgs/{org}/account-link/sddc-connections",
      "Method": [
        "GET"
      ]
    },
    "Cluster": {
      "Path": "/vmc/api/orgs/{org}/sddcs/{sddc}/primarycluster",
      "Method": [
        "GET"
      ]
    },
    "CompatibleSubnets": {
      "Path": "/vmc/api/orgs/{org}/account-link/compatible-subnets",
      "Method": [
        "GET"
      ],
      "QueryParams": {
        "forceRefresh": "true",
        "linkedAccountId": ""
      }
    },
    "ConnectedAccounts": {
      "Path": "/vmc/api/orgs/{org}/account-link/connected-accounts",
      "Method": [
        "GET"
      ]
    },
    "Credential": {
      "Path": "/vmc/api/orgs/{org}/sddcs/{sddc}/addons/HCX/credentials/{name}",
      "Method": [
        "GET"
      ]
    },
    "Credentials": {
      "Path": "/vmc/api/orgs/{org}/sddcs/{sddc}/addons/HCX/credentials",
      "Method": [
        "GET"
      ]
    },
    "CustomerSupport": {
      "Path": "/vmc/api/customer-support/inputs",
      "Method": [
        "GET"
      ],
      "QueryParams": {
        "orgId": "",
        "userID": ""
      }
    },
    "MsftLicensing": {
      "Path": "/vmc/api/orgs/{org}/tos",
      "Method": [
        "GET"
      ],
      "QueryParams": {
        "termsId": ""
      }
    },
    "NetworkConnChecker": {
      "Path": "/vmc/api/orgs/{org}/sddcs/{sddc}/networking/connectivity-tests",
      "Method": [
        "GET"
      ]
    },
    "OfferInstances": {
      "Path": "/vmc/api/orgs/{org}/subscriptions/offer-instances",
      "Method": [
        "GET"
      ],
      "QueryParams": {
        "product": "",
        "product_type": "",
        "region": "",
        "type": ""
      }
    },
    "Org": {
      "Path": "/vmc/api/orgs/{org}",
      "Method": [
        "GET"
      ]
    },
    "OrgPaymentMethods": {
      "Path": "/vmc/api/orgs/{org}/payment-methods",
      "Method": [
        "GET"
      ]
    },
    "OrgProviders": {
      "Path": "/vmc/api/orgs/{org}/providers",
      "Method": [
        "GET"
      ]
    },
    "Orgs": {
      "Path": "/vmc/api/orgs",
      "Method": [
        "GET"
      ]
    },
    "Products": {
      "Path": "/vmc/api/orgs/{org}/subscriptions/products",
      "Method": [
        "GET"
      ]
    },
    "ProvisionSpec": {
      "Path": "/vmc/api/orgs/{org}/sddcs/provision-spec",
      "Method": [
        "GET"
      ]
    },
    "Reservations": {
      "Path": "/vmc/api/orgs/{org}/reservations",
      "Method": [
        "GET"
      ]
    },
    "Sddc": {
      "Path": "/vmc/api/orgs/{org}/sddcs/{sddc}",
      "Method": [
        "GET"
      ]
    },
    "Sddcs": {
      "Path": "/vmc/api/orgs/{org}/sddcs",
      "Method": [
        "GET",
        "POST",
        "DELETE",
        "PATCH"
      ],
      "QueryParams": {
        "validateOnly": "true"
      }
    },
    "ServiceQuotaRequest": {
      "Path": "/vmc/api/orgs/{org}/aws/resources/servicequotas/requests/{serviceQuotaRequestId}Id",
      "Method": [
        "GET"
      ]
    },
    "ServiceQuotaRequests": {
      "Path": "/vmc/api/orgs/{org}/aws/resources/servicequotas/requests",
      "Method": [
        "GET"
      ]
    },
    "StorageSpecs": {
      "Path": "/vmc/api/orgs/{org}/sddcs/{sddc}/clusters/{cluster}/esxs/{esx}/storage-spec",
      "Method": [
        "GET"
      ]
    },
    "Subscription": {
      "Path": "/vmc/api/orgs/{org}/subscriptions/{subscription}",
      "Method": [
        "GET"
      ]
    },
    "Subscriptions": {
      "Path": "/vmc/api/orgs/{org}/subscriptions",
      "Method": [
        "GET"
      ]
    },
    "Task": {
      "Path": "/vmc/api/orgs/{org}/tasks/{task}",
      "Method": [
        "GET"
      ]
    },
    "Tasks": {
      "Path": "/vmc/api/orgs/{org}/tasks",
      "Method": [
        "GET"
      ],
      "QueryParams": {
        "$filter": "(updated gt 2022-07-15)"
      }
    },
    "Tbrs": {
      "Path": "/vmc/api/orgs/{org}/tbrs/support-window",
      "Method": [
        "GET"
      ]
    },
    "VsanClusterReconfigConstraints": {
      "Path": "/vmc/api/orgs/{org}/sddcs/{sddc}/clusters/{cluster}/config/constraints",
      "Method": [
        "GET"
      ]
    },
    "VsanConfigConstraints": {
      "Path": "/vmc/api/orgs/{org}/storage/cluster-constraints",
      "Method": [
        "GET"
      ],
      "QueryParams": {
        "num_hosts": "10",
        "provider": "AWS"
      }
    }
  },
  "Params": {
    "{cluster}": "",
    "{esx}": "",
    "{name}": "",
    "{org}": "",
    "{sddc}": "",
    "{serviceQuotaRequestId}": "",
    "{subscription}": "",
    "{task}": ""
  }
}